odoo9_addon_partner_contact_department-9.0.1.0.0-py2.7-nspkg.pth
odoo_addons/partner_contact_department/__openerp__.py
odoo_addons/partner_contact_department/__init__.py
odoo_addons/partner_contact_department/README.rst
odoo_addons/partner_contact_department/security/ir.model.access.csv
odoo_addons/partner_contact_department/models/res_partner.py
odoo_addons/partner_contact_department/models/__init__.py
odoo_addons/partner_contact_department/i18n/it.po
odoo_addons/partner_contact_department/i18n/es.po
odoo_addons/partner_contact_department/i18n/sl.po
odoo_addons/partner_contact_department/i18n/de.po
odoo_addons/partner_contact_department/i18n/fi.po
odoo_addons/partner_contact_department/views/res_partner_view.xml
odoo_addons/partner_contact_department/views/res_partner_department_view.xml
odoo_addons/partner_contact_department/tests/test_recursion.py
odoo_addons/partner_contact_department/tests/__init__.py
odoo_addons/partner_contact_department/static/description/icon.png
odoo9_addon_partner_contact_department-9.0.1.0.0.dist-info/top_level.txt
odoo9_addon_partner_contact_department-9.0.1.0.0.dist-info/WHEEL
odoo9_addon_partner_contact_department-9.0.1.0.0.dist-info/RECORD
odoo9_addon_partner_contact_department-9.0.1.0.0.dist-info/metadata.json
odoo9_addon_partner_contact_department-9.0.1.0.0.dist-info/DESCRIPTION.rst
odoo9_addon_partner_contact_department-9.0.1.0.0.dist-info/METADATA
odoo9_addon_partner_contact_department-9.0.1.0.0.dist-info/namespace_packages.txt
