Metadata-Version: 2.0
Name: odoo9-addon-partner-contact-department
Version: 9.0.1.0.0
Summary: Assign contacts to departments
Home-page: http://www.tecnativa.com
Author: UNKNOWN
Author-email: UNKNOWN
License: AGPL-3
Platform: UNKNOWN
Requires-Dist: odoo (<9.1a,>=9.0a)
Classifier: Programming Language :: Python :: 2.7
Classifier: Framework :: Odoo
Classifier: License :: OSI Approved :: GNU Affero General Public License v3
